gateau-0.2.0.dist-info/METADATA
gateau-0.2.0.dist-info/WHEEL
gateau/libgateau.so
gateau/__init__.py
gateau/__main__.py
gateau/atmosphere_utils.py
gateau/bind_utils.py
gateau/bindings.py
gateau/cascade.py
gateau/custom_logger.py
gateau/ifu.py
gateau/input_checker.py
gateau/materials.py
gateau/scan_patterns.py
gateau/selftest.py
gateau/simulator.py
gateau/source_utils.py
gateau/structs.py
gateau/threadmgr.py
gateau/types.py
gateau/resources/__init__.py
gateau/resources/eta_atm
gateau/resources/trans_data.dat
gateau-0.2.0.dist-info/RECORD
