Metadata-Version: 2.4
Name: gateau
Version: 0.2.0
Summary: GPU-Accelerated Time-dEpendent observAtion simUlator
Author: Arend Moerman
Author-Email: maybetree <maybetree48@proton.me>
License-Expression: AGPL-3.0-only
Classifier: Programming Language :: Python :: 3
Classifier: Programming Language :: C
Classifier: Programming Language :: C++
Classifier: Environment :: GPU :: NVIDIA CUDA :: 11
Classifier: Operating System :: OS Independent
Requires-Python: >=3.9
Requires-Dist: numpy
Requires-Dist: matplotlib
Requires-Dist: scipy
Requires-Dist: tqdm
Requires-Dist: astropy
Requires-Dist: psutil
Requires-Dist: h5py
Provides-Extra: dev
Requires-Dist: pip-tools; extra == "dev"
Requires-Dist: wheel-filename; extra == "dev"
Provides-Extra: doxy
Requires-Dist: jupyter; extra == "doxy"
